polars_hash/__init__.py
polars_hash/_internal.abi3.so
polars_hash/_internal.pyi
polars_hash/py.typed
polars_hash-0.5.6.dist-info/METADATA
polars_hash-0.5.6.dist-info/WHEEL
polars_hash-0.5.6.dist-info/RECORD
