Metadata-Version: 2.4
Name: polars-hash
Version: 0.5.6
Classifier: Programming Language :: Rust
Classifier: Programming Language :: Python :: Implementation :: CPython
Classifier: Programming Language :: Python :: Implementation :: PyPy
Requires-Dist: polars>=1.32.0
Summary: Stable non-cryptographic and cryptographic hashing functions for Polars
Author-email: Ion Koutsours <15728914+ion-elgreco@users.noreply.github.com>
Requires-Python: >=3.10
Project-URL: Bug Tracker, https://github.com/ion-elgreco/polars-hash/issues
Project-URL: Homepage, https://github.com/ion-elgreco/polars-hash
